{"name":"factory","backgroundTexture":"null","locations":[{"width":200.0,"height":200.0,"color":[255,255,255,255],"id":80,"x":261.0,"y":172.0,"rotation":-1.5703},{"width":200.0,"height":200.0,"color":[255,255,255,255],"id":80,"x":261.0,"y":543.0,"rotation":-1.5703},{"width":200.0,"height":200.0,"color":[255,255,255,255],"id":80,"x":891.0,"y":543.0,"rotation":-1.5703},{"width":200.0,"height":200.0,"color":[255,255,255,255],"id":80,"x":891.0,"y":172.0,"rotation":-1.5703},{"width":32.0,"height":32.0,"color":[255,255,255,255],"id":-2,"x":577.0,"y":357.0,"rotation":0.0}],"ambientPower":0.4,"ambientColor":{"red":255.0,"green":255.0,"blue":255.0}}